LICENSE
NOTICE.md
README.md
setup.py
outsystems/architecture_dashboard/__init__.py
outsystems/architecture_dashboard/ad_base.py
outsystems/architecture_dashboard/ad_tech_debt.py
outsystems/bdd_framework/__init__.py
outsystems/bdd_framework/bdd_base.py
outsystems/bdd_framework/bdd_runner.py
outsystems/cicd_probe/__init__.py
outsystems/cicd_probe/cicd_base.py
outsystems/cicd_probe/cicd_dependencies.py
outsystems/cicd_probe/cicd_scan.py
outsystems/exceptions/__init__.py
outsystems/exceptions/app_does_not_exist.py
outsystems/exceptions/app_version_error.py
outsystems/exceptions/deployment_not_found.py
outsystems/exceptions/environment_not_found.py
outsystems/exceptions/impossible_action_deployment.py
outsystems/exceptions/invalid_json_response.py
outsystems/exceptions/invalid_os_package.py
outsystems/exceptions/invalid_parameters.py
outsystems/exceptions/manifest_does_not_exist.py
outsystems/exceptions/no_apps_available.py
outsystems/exceptions/no_deployments.py
outsystems/exceptions/not_enough_permissions.py
outsystems/exceptions/osptool_error.py
outsystems/exceptions/server_error.py
outsystems/file_helpers/__init__.py
outsystems/file_helpers/file.py
outsystems/lifetime/__init__.py
outsystems/lifetime/lifetime_applications.py
outsystems/lifetime/lifetime_base.py
outsystems/lifetime/lifetime_deployments.py
outsystems/lifetime/lifetime_downloads.py
outsystems/lifetime/lifetime_environments.py
outsystems/lifetime/lifetime_solutions.py
outsystems/manifest/__init__.py
outsystems/manifest/manifest_base.py
outsystems/osp_tool/__init__.py
outsystems/osp_tool/osp_base.py
outsystems/pipeline/__init__.py
outsystems/pipeline/apply_configuration_values_to_target_env.py
outsystems/pipeline/continue_deployment_to_target_env.py
outsystems/pipeline/deploy_apps_to_target_env_with_airgap.py
outsystems/pipeline/deploy_latest_tags_to_target_env.py
outsystems/pipeline/deploy_package_to_target_env.py
outsystems/pipeline/deploy_package_to_target_env_with_osptool.py
outsystems_pipeline.egg-info/PKG-INFO
outsystems_pipeline.egg-info/SOURCES.txt
outsystems_pipeline.egg-info/dependency_links.txt
outsystems_pipeline.egg-info/requires.txt
outsystems_pipeline.egg-info/top_level.txt
