Metadata-Version: 2.1
Name: outsystems-pipeline
Version: 0.10.1
Summary: Python package to accelerate the integration of OutSystems with third-party CI/CD tools
Home-page: https://github.com/OutSystems/outsystems-pipeline
Author: OutSystems
Author-email: cicd.integrations@outsystems.com
License: Apache License 2.0
Classifier: Development Status :: 4 - Beta
Classifier: Intended Audience :: Developers
Classifier: Intended Audience :: System Administrators
Classifier: License :: OSI Approved :: Apache Software License
Classifier: Programming Language :: Python
Classifier: Topic :: Software Development :: Build Tools
Classifier: Topic :: Software Development :: Quality Assurance
Classifier: Topic :: Software Development :: Testing
Classifier: Topic :: Software Development :: Testing :: Acceptance
Classifier: Topic :: Software Development :: Testing :: BDD
Classifier: Topic :: Software Development :: Testing :: Unit
Classifier: Topic :: System :: Software Distribution
Requires-Python: >=3.8
License-File: LICENSE
License-File: NOTICE.md
